torchortho/__init__.py
torchortho/cuda.py
torchortho/fourier_activation.py
torchortho/hermite_activation.py
torchortho/tropical_activation.py
torchortho-0.1.2.dist-info/METADATA
torchortho-0.1.2.dist-info/WHEEL
torchortho-0.1.2.dist-info/licenses/LICENSE
torchortho-0.1.2.dist-info/RECORD
