Metadata-Version: 2.4
Name: torchortho
Version: 0.1.2
Summary: torchortho is a simple PyTorch package that efficiently implements the Hermite Activation function and other activation functions.
Project-URL: Homepage, https://github.com/K-H-Ismail/torchortho
Project-URL: Bug Tracker, https://github.com/K-H-Ismail/torchortho/issues
Author-email: Ismail Khalfaoui-Hassani <i.khalfaoui@fz-juelich.de>
License-File: LICENSE
Classifier: License :: OSI Approved :: GNU General Public License v3 or later (GPLv3+)
Classifier: Operating System :: OS Independent
Classifier: Programming Language :: Python :: 3.6
Requires-Python: >=3.6
